odoo/addons/shopinvader_v2_app_demo/README.rst
odoo/addons/shopinvader_v2_app_demo/__init__.py
odoo/addons/shopinvader_v2_app_demo/__manifest__.py
odoo/addons/shopinvader_v2_app_demo/demo/auth_jwt_validator.xml
odoo/addons/shopinvader_v2_app_demo/demo/fastapi_endpoint.xml
odoo/addons/shopinvader_v2_app_demo/demo/fs_storage.xml
odoo/addons/shopinvader_v2_app_demo/demo/res_groups.xml
odoo/addons/shopinvader_v2_app_demo/demo/res_users.xml
odoo/addons/shopinvader_v2_app_demo/demo/se_backend.xml
odoo/addons/shopinvader_v2_app_demo/demo/se_image_field_thumbnail_size.xml
odoo/addons/shopinvader_v2_app_demo/demo/se_index.xml
odoo/addons/shopinvader_v2_app_demo/demo/se_index_config.xml
odoo/addons/shopinvader_v2_app_demo/i18n/shopinvader_v2_app_demo.pot
odoo/addons/shopinvader_v2_app_demo/models/__init__.py
odoo/addons/shopinvader_v2_app_demo/models/fastapi_endpoint.py
odoo/addons/shopinvader_v2_app_demo/readme/CONTRIBUTORS.rst
odoo/addons/shopinvader_v2_app_demo/readme/DESCRIPTION.rst
odoo/addons/shopinvader_v2_app_demo/readme/HISTORY.rst
odoo/addons/shopinvader_v2_app_demo/static/description/icon.png
odoo/addons/shopinvader_v2_app_demo/static/description/index.html
odoo/addons/shopinvader_v2_app_demo/views/fastapi_endpoint.xml
odoo_addon_shopinvader_v2_app_demo-16.0.1.0.2.dist-info/METADATA
odoo_addon_shopinvader_v2_app_demo-16.0.1.0.2.dist-info/WHEEL
odoo_addon_shopinvader_v2_app_demo-16.0.1.0.2.dist-info/top_level.txt
odoo_addon_shopinvader_v2_app_demo-16.0.1.0.2.dist-info/RECORD
