Metadata-Version: 2.1
Name: odoo-addon-shopinvader_v2_app_demo
Version: 16.0.1.0.2
Summary: Adds a demo application on fastapi endpoint for a demo shopinvader application that takes every router
Home-page: https://github.com/shopinvader/odoo-shopinvader
Author: ACSONE SA/NV
License: AGPL-3
Classifier: Programming Language :: Python
Classifier: Framework :: Odoo
Classifier: Framework :: Odoo :: 16.0
Classifier: License :: OSI Approved :: GNU Affero General Public License v3
Requires-Python: >=3.10
Requires-Dist: fastapi
Requires-Dist: odoo-addon-connector-elasticsearch<16.1dev,>=16.0dev
Requires-Dist: odoo-addon-fastapi<16.1dev,>=16.0dev
Requires-Dist: odoo-addon-sale-channel-search-engine-category<16.1dev,>=16.0dev
Requires-Dist: odoo-addon-sale-channel-search-engine-product<16.1dev,>=16.0dev
Requires-Dist: odoo-addon-shopinvader-anonymous-partner<16.1dev,>=16.0dev
Requires-Dist: odoo-addon-shopinvader-api-address<16.1dev,>=16.0dev
Requires-Dist: odoo-addon-shopinvader-api-cart<16.1dev,>=16.0dev
Requires-Dist: odoo-addon-shopinvader-api-customer<16.1dev,>=16.0dev
Requires-Dist: odoo-addon-shopinvader-api-delivery-carrier<16.1dev,>=16.0dev
Requires-Dist: odoo-addon-shopinvader-api-payment-cart<16.1dev,>=16.0dev
Requires-Dist: odoo-addon-shopinvader-api-payment-provider-custom<16.1dev,>=16.0dev
Requires-Dist: odoo-addon-shopinvader-api-payment-provider-sips<16.1dev,>=16.0dev
Requires-Dist: odoo-addon-shopinvader-api-payment-provider-stripe<16.1dev,>=16.0dev
Requires-Dist: odoo-addon-shopinvader-api-sale<16.1dev,>=16.0dev
Requires-Dist: odoo-addon-shopinvader-api-sale-loyalty<16.1dev,>=16.0dev
Requires-Dist: odoo-addon-shopinvader-api-settings<16.1dev,>=16.0dev
Requires-Dist: odoo-addon-shopinvader-api-signin-jwt<16.1dev,>=16.0dev
Requires-Dist: odoo-addon-shopinvader-api-wishlist<16.1dev,>=16.0dev
Requires-Dist: odoo-addon-shopinvader-fastapi-auth-jwt<16.1dev,>=16.0dev
Requires-Dist: odoo-addon-shopinvader-product<16.1dev,>=16.0dev
Requires-Dist: odoo-addon-shopinvader-product-brand<16.1dev,>=16.0dev
Requires-Dist: odoo-addon-shopinvader-product-brand-tag<16.1dev,>=16.0dev
Requires-Dist: odoo-addon-shopinvader-product-description<16.1dev,>=16.0dev
Requires-Dist: odoo-addon-shopinvader-product-seo<16.1dev,>=16.0dev
Requires-Dist: odoo-addon-shopinvader-product-url<16.1dev,>=16.0dev
Requires-Dist: odoo-addon-shopinvader-search-engine<16.1dev,>=16.0dev
Requires-Dist: odoo-addon-shopinvader-search-engine-image<16.1dev,>=16.0dev
Requires-Dist: odoo-addon-shopinvader-search-engine-product-brand-image<16.1dev,>=16.0dev
Requires-Dist: odoo-addon-shopinvader-search-engine-product-price<16.1dev,>=16.0dev
Requires-Dist: odoo-addon-shopinvader-search-engine-product-stock-state<16.1dev,>=16.0dev
Requires-Dist: odoo-addon-shopinvader-search-engine-update-image<16.1dev,>=16.0dev
Requires-Dist: odoo-addon-shopinvader-search-engine-update-product-brand<16.1dev,>=16.0dev
Requires-Dist: odoo-addon-shopinvader-search-engine-update-product-brand-image<16.1dev,>=16.0dev
Requires-Dist: odoo-addon-shopinvader-search-engine-update-product-media<16.1dev,>=16.0dev
Requires-Dist: odoo-addon-shopinvader-search-engine-update-product-template-multi-link<16.1dev,>=16.0dev
Requires-Dist: odoo<16.1dev,>=16.0a
